punkr/__init__.py
punkr/punkr.py
punkr/rpc_client.py
punkr-1.0.0.dist-info/LICENSE
punkr-1.0.0.dist-info/METADATA
punkr-1.0.0.dist-info/WHEEL
punkr-1.0.0.dist-info/top_level.txt
punkr-1.0.0.dist-info/RECORD
