Metadata-Version: 2.1
Name: punkr
Version: 1.0.0
Summary: Bunkr operations wrapper
Home-page: UNKNOWN
Author: off-the-grid-inc
Author-email: accounts@off-the-grid.io
License: UNKNOWN
Platform: UNKNOWN
Classifier: Programming Language :: Python :: 3
Classifier: Operating System :: OS Independent
